pyvdv736-0.1.7.dist-info/licenses/LICENSE.md
vdv736/__init__.py
vdv736/database.py
vdv736/datalog.py
vdv736/delivery.py
vdv736/isotime.py
vdv736/model.py
vdv736/participantconfig.py
vdv736/publisher.py
vdv736/request.py
vdv736/response.py
vdv736/sirixml.py
vdv736/subscriber.py
vdv736/version.py
pyvdv736-0.1.7.dist-info/METADATA
pyvdv736-0.1.7.dist-info/WHEEL
pyvdv736-0.1.7.dist-info/top_level.txt
pyvdv736-0.1.7.dist-info/RECORD
