Metadata-Version: 2.4
Name: pyvdv736
Version: 0.1.7
Summary: Simple reference implementation for VDV 736 subscriber and publisher written in Python
Author-email: Sebastian Knopf <mail@sebastian-knopf.de>
License: Apache License (2.0)
Requires-Python: >=3.10
License-File: LICENSE.md
Requires-Dist: fastapi[all]
Requires-Dist: lxml
Requires-Dist: pyyaml
Requires-Dist: requests
Requires-Dist: uvicorn
Provides-Extra: test
Requires-Dist: responses; extra == "test"
Provides-Extra: all
Requires-Dist: pyvdv736[test]; extra == "all"
Dynamic: license-file
